dis_taipan/__init__.py
dis_taipan/botguild.py
dis_taipan/protocols.py
dis_taipan/py.typed
dis_taipan/sentry.py
dis_taipan/updater.py
dis_taipan-0.3.0.dist-info/METADATA
dis_taipan-0.3.0.dist-info/WHEEL
dis_taipan-0.3.0.dist-info/top_level.txt
dis_taipan-0.3.0.dist-info/RECORD
