Metadata-Version: 2.1
Name: dis-taipan
Version: 0.3.0
Summary: A handful of naff extensions that I want to use in most of my bots.
Home-page: https://github.com/silasary/dis-taipan
Author: Silasary
Classifier: Programming Language :: Python :: 3
Classifier: License :: OSI Approved :: MIT License
Classifier: Operating System :: OS Independent
Requires-Python: >=3.10
Requires-Dist: naff (>=1.8.1)
Requires-Dist: sentry-sdk
